cuaffils-1.0.0.dist-info/top_level.txt
cuaffils-1.0.0.dist-info/metadata.json
cuaffils-1.0.0.dist-info/METADATA
cuaffils-1.0.0.dist-info/DESCRIPTION.rst
cuaffils-1.0.0.dist-info/RECORD
cuaffils-1.0.0.dist-info/WHEEL
cuaffils/__init__.py
cuaffils/affils.pyc
cuaffils/affils.py
cuaffils/__init__.pyc
