Metadata-Version: 2.0
Name: cuaffils
Version: 1.0.0
Summary: CU affil strings
Home-page: UNKNOWN
Author: Anders Pearson
Author-email: anders@columbia.edu
License: BSD
Platform: any
